netkit/__init__.py
netkit/box.py
netkit/log.py
netkit/stream.py
netkit/utils.py
netkit/contrib/__init__.py
netkit/contrib/tcp_client.py
netkit-3.1.12.dist-info/METADATA
netkit-3.1.12.dist-info/WHEEL
netkit-3.1.12.dist-info/top_level.txt
netkit-3.1.12.dist-info/RECORD
