Metadata-Version: 2.1
Name: netkit
Version: 3.1.12
Summary: useful kit for network programming
Home-page: https://github.com/dantezhu/netkit
Author: dantezhu
Author-email: dantezhu <zny2008@gmail.com>
License: MIT
Project-URL: Homepage, https://github.com/dantezhu/netkit
Requires-Python: >=3
